[
  {
    "LiveFrom": "01/06/2024",
    "CaseTypeID": "PRLAPPS",
    "ID": "markAsPrivateDisclaimer",
    "Label": "## Before you start \n\nRestricted cases will not appear in search results. \n\nThey can only be accessed by people who have been given the right permissions.",
    "FieldType": "Label",
    "SecurityClassification": "Public"
  },
  {
    "LiveFrom": "01/06/2024",
    "CaseTypeID": "PRLAPPS",
    "ID": "markAsPrivateReasonLabel",
    "Label": "### Enter the reasons to make this case private",
    "FieldType": "Label",
    "SecurityClassification": "Public"
  },
  {
    "LiveFrom": "01/06/2024",
    "CaseTypeID": "PRLAPPS",
    "ID": "markAsPrivateReasonText",
    "Label": "Briefly explain why this case should be restricted.",
    "FieldType": "TextArea",
    "SecurityClassification": "Public"
  }
]