[
  {
    "LiveFrom": "03/11/2021",
    "CaseTypeID": "PRLAPPS",
    "CaseEventID": "miamPolicyUpgrade",
    "CaseFieldID": "submissionRequiredFieldsInfo9",
    "PageFieldDisplayOrder": 1,
    "DisplayContext": "READONLY",
    "PageID": 9,
    "PageDisplayOrder": 9,
    "ShowSummaryChangeOption": "N",
    "PageShowCondition": "claimingExemptionMiam=\"Yes\" AND applicantAttendedMiam=\"No\" AND childInvolvedInMIAM=\"No\" AND miamPolicyUpgradeExemptionsChecklist CONTAINS \"childProtectionConcern\""
  },
  {
    "LiveFrom": "05/01/2022",
    "CaseTypeID": "PRLAPPS",
    "CaseEventID": "miamPolicyUpgrade",
    "CaseFieldID": "miamExemptionLabel9",
    "PageFieldDisplayOrder": 2,
    "DisplayContext": "READONLY",
    "PageID": 9,
    "PageDisplayOrder": 9,
    "ShowSummaryChangeOption": "Y"
  },
  {
    "LiveFrom": "05/01/2022",
    "CaseTypeID": "PRLAPPS",
    "CaseEventID": "miamPolicyUpgrade",
    "CaseFieldID": "miamPolicyUpgradeChildProtectionConcernList",
    "PageFieldDisplayOrder": 3,
    "DisplayContext": "MANDATORY",
    "PageID": 9,
    "PageDisplayOrder": 9,
    "ShowSummaryChangeOption": "Y"
  }
]
