[
  {
    "LiveFrom": "11/05/2022",
    "CaseTypeID": "PRLAPPS",
    "CaseEventID": "serviceOfApplication",
    "CaseFieldID": "serviceOfApplicationHeader",
    "PageFieldDisplayOrder": 0,
    "DisplayContext": "READONLY",
    "PageID": "orderDetails",
    "PageDisplayOrder": 1,
    "ShowSummaryChangeOption": "Y"
  },
  {
    "LiveFrom": "11/05/2022",
    "CaseTypeID": "PRLAPPS",
    "CaseEventID": "serviceOfApplication",
    "CaseFieldID": "serveTheseOrdersLabel",
    "PageFieldDisplayOrder": 1,
    "DisplayContext": "READONLY",
    "PageID": "orderDetails",
    "PageDisplayOrder": 1,
    "ShowSummaryChangeOption": "Y"
  },
  {
    "LiveFrom": "11/05/2022",
    "CaseTypeID": "PRLAPPS",
    "CaseEventID": "serviceOfApplication",
    "CaseFieldID": "automaticDocumentsLabel",
    "PageFieldDisplayOrder": 2,
    "DisplayContext": "READONLY",
    "PageID": "orderDetails",
    "PageDisplayOrder": 1,
    "ShowSummaryChangeOption": "Y"
  },
  {
    "LiveFrom": "11/05/2022",
    "CaseTypeID": "PRLAPPS",
    "CaseEventID": "serviceOfApplication",
    "CaseFieldID": "sentDocumentPlaceHolder",
    "PageFieldDisplayOrder": 0,
    "DisplayContext": "OPTIONAL",
    "PageID": "orderDetails",
    "PageDisplayOrder": 1,
    "ShowSummaryChangeOption": "Y",
    "FieldShowCondition": "serviceOfApplicationScreen1=\"DO NOT SHOW\""
  },
  {
    "LiveFrom": "11/05/2022",
    "CaseTypeID": "PRLAPPS",
    "CaseEventID": "serviceOfApplication",
    "CaseFieldID": "sentDocumentsLabel",
    "PageFieldDisplayOrder": 3,
    "DisplayContext": "READONLY",
    "PageID": "orderDetails",
    "PageDisplayOrder": 1,
    "ShowSummaryChangeOption": "Y"
  },

  {
    "LiveFrom": "11/05/2022",
    "CaseTypeID": "PRLAPPS",
    "CaseEventID": "serviceOfApplication",
    "CaseFieldID": "serviceOfApplicationScreen1",
    "PageFieldDisplayOrder": 4,
    "DisplayContext": "COMPLEX",
    "PageID": "orderDetails",
    "PageDisplayOrder": 1,
    "ShowSummaryChangeOption": "Y"
  },
  {
    "LiveFrom": "11/05/2022",
    "CaseTypeID": "PRLAPPS",
    "CaseEventID": "serviceOfApplication",
    "CaseFieldID": "pd36qLetterLabel",
    "PageFieldDisplayOrder": 5,
    "DisplayContext": "READONLY",
    "PageID": "orderDetails",
    "PageDisplayOrder": 1,
    "ShowSummaryChangeOption": "Y"
  },
  {
    "LiveFrom": "11/05/2022",
    "CaseTypeID": "PRLAPPS",
    "CaseEventID": "serviceOfApplication",
    "CaseFieldID": "specialArrangementsLetterLabel",
    "PageFieldDisplayOrder": 7,
    "DisplayContext": "READONLY",
    "PageID": "orderDetails",
    "PageDisplayOrder": 1,
    "ShowSummaryChangeOption": "Y"
  },
  {
    "LiveFrom": "11/05/2022",
    "CaseTypeID": "PRLAPPS",
    "CaseEventID": "serviceOfApplication",
    "CaseFieldID": "additionalDocumentsLabel",
    "PageFieldDisplayOrder": 9,
    "DisplayContext": "READONLY",
    "PageID": "orderDetails",
    "PageDisplayOrder": 1,
    "ShowSummaryChangeOption": "Y"
  },
  {
    "LiveFrom": "11/05/2022",
    "CaseTypeID": "PRLAPPS",
    "CaseEventID": "serviceOfApplication",
    "CaseFieldID": "pd36qLetter",
    "PageFieldDisplayOrder": 6,
    "DisplayContext": "OPTIONAL",
    "PageID": "orderDetails",
    "PageDisplayOrder": 1,
    "ShowSummaryChangeOption": "Y"
  },
  {
    "LiveFrom": "11/05/2022",
    "CaseTypeID": "PRLAPPS",
    "CaseEventID": "serviceOfApplication",
    "CaseFieldID": "specialArrangementsLetter",
    "PageFieldDisplayOrder": 8,
    "DisplayContext": "OPTIONAL",
    "PageID": "orderDetails",
    "PageDisplayOrder": 1,
    "ShowSummaryChangeOption": "Y"
  },
  {
    "LiveFrom": "11/05/2022",
    "CaseTypeID": "PRLAPPS",
    "CaseEventID": "serviceOfApplication",
    "CaseFieldID": "additionalDocuments",
    "PageFieldDisplayOrder": 10,
    "DisplayContext": "OPTIONAL",
    "PageID": "orderDetails",
    "PageDisplayOrder": 1,
    "ShowSummaryChangeOption": "Y"
  },
  {
    "LiveFrom": "11/05/2022",
    "CaseTypeID": "PRLAPPS",
    "CaseEventID": "serviceOfApplication",
    "CaseFieldID": "confirmRecipients",
    "PageFieldDisplayOrder": 1,
    "DisplayContext": "COMPLEX",
    "PageID": "confirmRecipients",
    "PageDisplayOrder": 2,
    "ShowSummaryChangeOption": "Y"
  },
  {
    "LiveFrom": "11/05/2022",
    "CaseTypeID": "PRLAPPS",
    "CaseEventID": "serviceOfApplication",
    "CaseFieldID": "headerLabel",
    "PageFieldDisplayOrder": 0,
    "DisplayContext": "READONLY",
    "PageID": "confirmRecipients",
    "PageDisplayOrder": 2,
    "ShowSummaryChangeOption": "Y"
  },

  {
    "LiveFrom": "11/05/2022",
    "CaseTypeID": "PRLAPPS",
    "CaseEventID": "serviceOfApplication",
    "CaseFieldID": "option1",
    "PageFieldDisplayOrder": 10,
    "DisplayContext": "OPTIONAL",
    "PageID": "orderDetails",
    "FieldShowCondition": "sentDocumentPlaceHolder=\"DO_NOT_SHOW\"",
    "PageDisplayOrder": 1,
    "ShowSummaryChangeOption": "Y"
  },
  {
    "LiveFrom": "11/05/2022",
    "CaseTypeID": "PRLAPPS",
    "CaseEventID": "serviceOfApplication",
    "CaseFieldID": "option2",
    "PageFieldDisplayOrder": 10,
    "DisplayContext": "OPTIONAL",
    "PageID": "orderDetails",
    "FieldShowCondition": "sentDocumentPlaceHolder=\"DO_NOT_SHOW\"",
    "PageDisplayOrder": 1,
    "ShowSummaryChangeOption": "Y"
  },
  {
    "LiveFrom": "11/05/2022",
    "CaseTypeID": "PRLAPPS",
    "CaseEventID": "serviceOfApplication",
    "CaseFieldID": "option3",
    "PageFieldDisplayOrder": 10,
    "DisplayContext": "OPTIONAL",
    "PageID": "orderDetails",
    "FieldShowCondition": "sentDocumentPlaceHolder=\"DO_NOT_SHOW\"",
    "PageDisplayOrder": 1,
    "ShowSummaryChangeOption": "Y"
  },
  {
    "LiveFrom": "11/05/2022",
    "CaseTypeID": "PRLAPPS",
    "CaseEventID": "serviceOfApplication",
    "CaseFieldID": "option4",
    "PageFieldDisplayOrder": 10,
    "DisplayContext": "OPTIONAL",
    "PageID": "orderDetails",
    "FieldShowCondition": "sentDocumentPlaceHolder=\"DO_NOT_SHOW\"",
    "PageDisplayOrder": 1,
    "ShowSummaryChangeOption": "Y"
  },
  {
    "LiveFrom": "11/05/2022",
    "CaseTypeID": "PRLAPPS",
    "CaseEventID": "serviceOfApplication",
    "CaseFieldID": "option5",
    "PageFieldDisplayOrder": 10,
    "DisplayContext": "OPTIONAL",
    "PageID": "orderDetails",
    "FieldShowCondition": "sentDocumentPlaceHolder=\"DO_NOT_SHOW\"",
    "PageDisplayOrder": 1,
    "ShowSummaryChangeOption": "Y"
  },
  {
    "LiveFrom": "11/05/2022",
    "CaseTypeID": "PRLAPPS",
    "CaseEventID": "serviceOfApplication",
    "CaseFieldID": "option6",
    "PageFieldDisplayOrder": 10,
    "DisplayContext": "OPTIONAL",
    "PageID": "orderDetails",
    "FieldShowCondition": "sentDocumentPlaceHolder=\"DO_NOT_SHOW\"",
    "PageDisplayOrder": 1,
    "ShowSummaryChangeOption": "Y"
  },
  {
    "LiveFrom": "11/05/2022",
    "CaseTypeID": "PRLAPPS",
    "CaseEventID": "serviceOfApplication",
    "CaseFieldID": "option7",
    "PageFieldDisplayOrder": 10,
    "DisplayContext": "OPTIONAL",
    "PageID": "orderDetails",
    "FieldShowCondition": "sentDocumentPlaceHolder=\"DO_NOT_SHOW\"",
    "PageDisplayOrder": 1,
    "ShowSummaryChangeOption": "Y"
  },
  {
    "LiveFrom": "11/05/2022",
    "CaseTypeID": "PRLAPPS",
    "CaseEventID": "serviceOfApplication",
    "CaseFieldID": "option8",
    "PageFieldDisplayOrder": 10,
    "DisplayContext": "OPTIONAL",
    "PageID": "orderDetails",
    "FieldShowCondition": "sentDocumentPlaceHolder=\"DO_NOT_SHOW\"",
    "PageDisplayOrder": 1,
    "ShowSummaryChangeOption": "Y"
  },
  {
    "LiveFrom": "11/05/2022",
    "CaseTypeID": "PRLAPPS",
    "CaseEventID": "serviceOfApplication",
    "CaseFieldID": "option9",
    "PageFieldDisplayOrder": 10,
    "DisplayContext": "OPTIONAL",
    "PageID": "orderDetails",
    "FieldShowCondition": "sentDocumentPlaceHolder=\"DO_NOT_SHOW\"",
    "PageDisplayOrder": 1,
    "ShowSummaryChangeOption": "Y"
  },
  {
    "LiveFrom": "11/05/2022",
    "CaseTypeID": "PRLAPPS",
    "CaseEventID": "serviceOfApplication",
    "CaseFieldID": "option10",
    "PageFieldDisplayOrder": 10,
    "DisplayContext": "OPTIONAL",
    "PageID": "orderDetails",
    "FieldShowCondition": "sentDocumentPlaceHolder=\"DO_NOT_SHOW\"",
    "PageDisplayOrder": 1,
    "ShowSummaryChangeOption": "Y"
  },
  {
    "LiveFrom": "11/05/2022",
    "CaseTypeID": "PRLAPPS",
    "CaseEventID": "serviceOfApplication",
    "CaseFieldID": "option11",
    "PageFieldDisplayOrder": 10,
    "DisplayContext": "OPTIONAL",
    "PageID": "orderDetails",
    "FieldShowCondition": "sentDocumentPlaceHolder=\"DO_NOT_SHOW\"",
    "PageDisplayOrder": 1,
    "ShowSummaryChangeOption": "Y"
  },
  {
    "LiveFrom": "11/05/2022",
    "CaseTypeID": "PRLAPPS",
    "CaseEventID": "serviceOfApplication",
    "CaseFieldID": "option12",
    "PageFieldDisplayOrder": 10,
    "DisplayContext": "OPTIONAL",
    "PageID": "orderDetails",
    "FieldShowCondition": "sentDocumentPlaceHolder=\"DO_NOT_SHOW\"",
    "PageDisplayOrder": 1,
    "ShowSummaryChangeOption": "Y"
  },
  {
    "LiveFrom": "11/05/2022",
    "CaseTypeID": "PRLAPPS",
    "CaseEventID": "serviceOfApplication",
    "CaseFieldID": "option13",
    "PageFieldDisplayOrder": 10,
    "DisplayContext": "OPTIONAL",
    "PageID": "orderDetails",
    "FieldShowCondition": "sentDocumentPlaceHolder=\"DO_NOT_SHOW\"",
    "PageDisplayOrder": 1,
    "ShowSummaryChangeOption": "Y"
  },
  {
    "LiveFrom": "11/05/2022",
    "CaseTypeID": "PRLAPPS",
    "CaseEventID": "serviceOfApplication",
    "CaseFieldID": "option14",
    "PageFieldDisplayOrder": 10,
    "DisplayContext": "OPTIONAL",
    "PageID": "orderDetails",
    "FieldShowCondition": "sentDocumentPlaceHolder=\"DO_NOT_SHOW\"",
    "PageDisplayOrder": 1,
    "ShowSummaryChangeOption": "Y"
  },
  {
    "LiveFrom": "11/05/2022",
    "CaseTypeID": "PRLAPPS",
    "CaseEventID": "serviceOfApplication",
    "CaseFieldID": "option15",
    "PageFieldDisplayOrder": 10,
    "DisplayContext": "OPTIONAL",
    "PageID": "orderDetails",
    "FieldShowCondition": "sentDocumentPlaceHolder=\"DO_NOT_SHOW\"",
    "PageDisplayOrder": 1,
    "ShowSummaryChangeOption": "Y"
  },
  {
    "LiveFrom": "11/05/2022",
    "CaseTypeID": "PRLAPPS",
    "CaseEventID": "serviceOfApplication",
    "CaseFieldID": "option16",
    "PageFieldDisplayOrder": 10,
    "DisplayContext": "OPTIONAL",
    "PageID": "orderDetails",
    "FieldShowCondition": "sentDocumentPlaceHolder=\"DO_NOT_SHOW\"",
    "PageDisplayOrder": 1,
    "ShowSummaryChangeOption": "Y"
  },
  {
    "LiveFrom": "11/05/2022",
    "CaseTypeID": "PRLAPPS",
    "CaseEventID": "serviceOfApplication",
    "CaseFieldID": "option17",
    "PageFieldDisplayOrder": 10,
    "DisplayContext": "OPTIONAL",
    "PageID": "orderDetails",
    "FieldShowCondition": "sentDocumentPlaceHolder=\"DO_NOT_SHOW\"",
    "PageDisplayOrder": 1,
    "ShowSummaryChangeOption": "Y"
  },
  {
    "LiveFrom": "11/05/2022",
    "CaseTypeID": "PRLAPPS",
    "CaseEventID": "serviceOfApplication",
    "CaseFieldID": "caseTypeOfApplication",
    "PageFieldDisplayOrder": 0,
    "DisplayContext": "READONLY",
    "PageID": "confirmRecipients",
    "PageDisplayOrder": 2,
    "ShowSummaryChangeOption": "N",
    "FieldShowCondition": "serveTheseOrdersLabel=\"DO_NOT_SHOW\"",
    "Publish" : "True"
  }
]
