[
  {
    "LiveFrom": "20/08/2021",
    "CaseTypeID": "PRLAPPS",
    "ID": "Child",
    "CaseEventID": "childDetailsRevised",
    "CaseFieldID": "children",
    "ListElementCode": "firstName",
    "EventElementLabel": "",
    "FieldDisplayOrder": "1",
    "DisplayContext": "OPTIONAL"
  },
  {
    "LiveFrom": "20/08/2021",
    "CaseTypeID": "PRLAPPS",
    "ID": "Child",
    "CaseEventID": "childDetailsRevised",
    "CaseFieldID": "children",
    "ListElementCode": "lastName",
    "EventElementLabel": "",
    "FieldDisplayOrder": "2",
    "DisplayContext": "OPTIONAL"
  },
  {
    "LiveFrom": "20/08/2021",
    "CaseTypeID": "PRLAPPS",
    "ID": "Child",
    "CaseEventID": "childDetailsRevised",
    "CaseFieldID": "children",
    "ListElementCode": "dateOfBirth",
    "EventElementLabel": "",
    "FieldDisplayOrder": "3",
    "DisplayContext": "OPTIONAL"
  },
  {
    "LiveFrom": "20/08/2021",
    "CaseTypeID": "PRLAPPS",
    "ID": "Child",
    "CaseEventID": "childDetailsRevised",
    "CaseFieldID": "children",
    "ListElementCode": "gender",
    "EventElementLabel": "",
    "FieldDisplayOrder": "4",
    "DisplayContext": "OPTIONAL"
  },
  {
    "LiveFrom": "05/11/2021",
    "CaseTypeID": "PRLAPPS",
    "ID": "Child",
    "CaseEventID": "childDetailsRevised",
    "CaseFieldID": "children",
    "DisplayContext": "OPTIONAL",
    "ListElementCode": "otherGender",
    "EventElementLabel": "",
    "FieldDisplayOrder": "5",
    "FieldShowCondition": "children.gender=\"other\""
  },
  {
    "LiveFrom": "20/08/2021",
    "CaseTypeID": "PRLAPPS",
    "ID": "Child",
    "CaseEventID": "childDetailsRevised",
    "CaseFieldID": "children",
    "ListElementCode": "orderAppliedFor",
    "EventElementLabel": "",
    "FieldDisplayOrder": "6",
    "DisplayContext": "OPTIONAL"
  },
  {
    "LiveFrom": "05/11/2021",
    "CaseTypeID": "PRLAPPS",
    "ID": "Child",
    "CaseEventID": "childDetailsRevised",
    "CaseFieldID": "children",
    "ListElementCode": "parentalResponsibility",
    "EventElementLabel": "",
    "FieldDisplayOrder": "7",
    "DisplayContext": "READONLY"
  },
  {
    "LiveFrom": "05/11/2021",
    "CaseTypeID": "PRLAPPS",
    "ID": "Child",
    "CaseEventID": "childDetailsRevised",
    "CaseFieldID": "children",
    "ListElementCode": "parentalResponsibilityDetails",
    "EventElementLabel": "",
    "FieldDisplayOrder": "8",
    "DisplayContext": "OPTIONAL"
  },
  {
    "LiveFrom": "20/08/2021",
    "CaseTypeID": "PRLAPPS",
    "ID": "Child",
    "CaseEventID": "childDetailsRevised",
    "CaseFieldID": "children",
    "ListElementCode": "addNewChildLabel",
    "EventElementLabel": "",
    "FieldDisplayOrder": "9",
    "DisplayContext": "MANDATORY"
  }
]