[
  {
    "LiveFrom": "21/11/2021",
    "CaseTypeID": "PRLAPPS",
    "CaseEventID": "otherProceedings",
    "AccessControl": [
      {
        "UserRoles": [
          "[APPLICANTSOLICITOR]",
          "[CREATOR]",
          "citizen",
          "caseworker-privatelaw-systemupdate",
          "caseworker-privatelaw-courtadmin"
        ],
        "CRUD": "CRU"
      },
      {
        "UserRoles": [
          "caseworker-privatelaw-judge",
          "caseworker-privatelaw-la",
          "caseworker-privatelaw-superuser"
        ],
        "CRUD": "R"
      }
    ]
  }
]