[
  {
    "LiveFrom": "20/08/2021",
    "ID": "UploadedDocuments",
    "ListElementCode": "parentDocumentType",
    "FieldType": "Text",
    "ElementLabel": "Parent document type",
    "SecurityClassification": "Public",
    "Searchable": "N"
  },
  {
    "LiveFrom": "20/08/2021",
    "ID": "UploadedDocuments",
    "ListElementCode": "documentType",
    "FieldType": "Text",
    "ElementLabel": "Document type",
    "SecurityClassification": "Public",
    "Searchable": "N"
  },
  {
    "LiveFrom": "20/08/2021",
    "ID": "UploadedDocuments",
    "ListElementCode": "partyName",
    "FieldType": "Text",
    "ElementLabel": "Name",
    "SecurityClassification": "Public",
    "Searchable": "N"
  },
  {
    "LiveFrom": "20/08/2021",
    "ID": "UploadedDocuments",
    "ListElementCode": "isApplicant",
    "FieldType": "Text",
    "ElementLabel": "Uploaded by applicant",
    "FieldShowCondition": "[STATE]=\"NEVER_SHOW\"",
    "SecurityClassification": "Public",
    "Searchable": "N"
  },
  {
    "LiveFrom": "20/08/2021",
    "ID": "UploadedDocuments",
    "ListElementCode": "uploadedBy",
    "FieldType": "Text",
    "ElementLabel": "party id",
    "FieldShowCondition": "[STATE]=\"NEVER_SHOW\"",
    "SecurityClassification": "Public",
    "Searchable": "N"
  },
  {
    "LiveFrom": "20/08/2021",
    "ID": "UploadedDocuments",
    "ListElementCode": "dateCreated",
    "FieldType": "Date",
    "ElementLabel": "Creation date",
    "SecurityClassification": "Public",
    "Searchable": "N"
  },
  {
    "LiveFrom": "20/08/2021",
    "ID": "UploadedDocuments",
    "ListElementCode": "documentDetails",
    "FieldType": "DocumentDetails",
    "ElementLabel": "Document details",
    "SecurityClassification": "Public",
    "Searchable": "N"
  },
  {
    "LiveFrom": "20/08/2021",
    "ID": "UploadedDocuments",
    "ListElementCode": "citizenDocument",
    "FieldType": "Document",
    "ElementLabel": "Uploaded document",
    "SecurityClassification": "Public",
    "Searchable": "N",
    "CategoryID": "citizenQuarantine"
  },
  {
    "LiveFrom": "20/08/2021",
    "ID": "UploadedDocuments",
    "ListElementCode": "cafcassDocument",
    "FieldType": "Document",
    "ElementLabel": "Cafcass document",
    "SecurityClassification": "Public",
    "Searchable": "N",
    "CategoryID": "safeguardingLetter"
  },
  {
    "LiveFrom": "20/08/2021",
    "ID": "UploadedDocuments",
    "ListElementCode": "documentRequestedByCourt",
    "FieldType": "YesOrNo",
    "ElementLabel": "Is document requested by court to upload?",
    "FieldShowCondition": "[STATE]=\"NEVER_SHOW\"",
    "SecurityClassification": "Public",
    "Searchable": "N"
  }
]