[
  {
    "LiveFrom": "20/08/2021",
    "ID": "Response",
    "ListElementCode": "legalRepresentation",
    "FieldType": "YesOrNo",
    "ElementLabel": " ",
    "SecurityClassification": "Public"
  },
  {
    "LiveFrom": "20/08/2021",
    "ID": "Response",
    "ListElementCode": "consent",
    "FieldType": "Consent",
    "ElementLabel": " ",
    "SecurityClassification": "Public"
  },
  {
    "LiveFrom": "20/08/2021",
    "ID": "Response",
    "ListElementCode": "keepDetailsPrivate",
    "FieldType": "KeepDetailsPrivate",
    "ElementLabel": " ",
    "SecurityClassification": "Public"
  },
  {
    "LiveFrom": "20/08/2021",
    "ID": "Response",
    "ListElementCode": "citizenDetails",
    "FieldType": "CitizenDetails",
    "ElementLabel": " ",
    "SecurityClassification": "Public"
  },
  {
    "LiveFrom": "20/08/2021",
    "ID": "Response",
    "ListElementCode": "citizenFlags",
    "FieldType": "CitizenFlags",
    "ElementLabel": " ",
    "SecurityClassification": "Public"
  },
  {
    "LiveFrom": "20/08/2021",
    "ID": "Response",
    "ListElementCode": "miam",
    "FieldType": "Miam",
    "ElementLabel": " ",
    "SecurityClassification": "Public"
  },
  {
    "LiveFrom": "20/08/2021",
    "ID": "Response",
    "ListElementCode": "currentOrPreviousProceedings",
    "FieldType": "CurrentOrPreviousProceedings",
    "ElementLabel": " ",
    "SecurityClassification": "Public"
  },
  {
    "LiveFrom": "20/08/2021",
    "ID": "Response",
    "ListElementCode": "citizenInternationalElements",
    "FieldType": "CitizenInternationalElements",
    "ElementLabel": " ",
    "SecurityClassification": "Public"
  },
  {
    "LiveFrom": "20/08/2021",
    "ID": "Response",
    "ListElementCode": "safeToCallOption",
    "FieldType": "Text",
    "ElementLabel": " ",
    "SecurityClassification": "Public"
  },
  {
    "LiveFrom": "20/08/2021",
    "ID": "Response",
    "ListElementCode": "activeRespondent",
    "FieldType": "YesOrNo",
    "ElementLabel": " ",
    "SecurityClassification": "Public"
  },
  {
    "LiveFrom": "20/08/2021",
    "ID": "Response",
    "ListElementCode": "c7ResponseSubmitted",
    "FieldType": "YesOrNo",
    "ElementLabel": " ",
    "SecurityClassification": "Public"
  },
  {
    "LiveFrom": "20/08/2021",
    "ID": "Response",
    "ListElementCode": "c1AResponseSubmitted",
    "FieldType": "YesOrNo",
    "ElementLabel": " ",
    "SecurityClassification": "Public"
  }
]