[
  {
    "LiveFrom": "03/11/2021",
    "CaseTypeID": "PRLAPPS",
    "CaseEventID": "allegationsOfHarmRevised",
    "CaseFieldID": "submissionRequiredFieldsInfo1",
    "PageFieldDisplayOrder": 1,
    "DisplayContext": "READONLY",
    "PageID": 1,
    "PageDisplayOrder": 1,
    "ShowSummaryChangeOption": "N"
  },
  {
    "LiveFrom": "17/11/2021",
    "CaseTypeID": "PRLAPPS",
    "CaseEventID": "allegationsOfHarmRevised",
    "CaseFieldID": "allegationsOfHarmRevisedHint",
    "DisplayContext": "READONLY",
    "PageID": 1,
    "PageDisplayOrder": 1,
    "PageFieldDisplayOrder": 2,
    "FieldShowCondition": "newAllegationsOfHarmYesNo=\"Yes\"",
    "ShowSummaryChangeOption": "Yes"
  },
  {
    "LiveFrom": "17/11/2021",
    "CaseTypeID": "PRLAPPS",
    "CaseEventID": "allegationsOfHarmRevised",
    "CaseFieldID": "newAllegationsOfHarmYesNo",
    "DisplayContext": "OPTIONAL",
    "PageID": 1,
    "PageDisplayOrder": 1,
    "PageFieldDisplayOrder": 3,
    "ShowSummaryChangeOption": "Yes"
  },
  {
    "LiveFrom": "03/11/2021",
    "CaseTypeID": "PRLAPPS",
    "CaseEventID": "allegationsOfHarmRevised",
    "CaseFieldID": "submissionRequiredFieldsInfo2",
    "PageFieldDisplayOrder": 1,
    "DisplayContext": "READONLY",
    "PageID": 2,
    "PageDisplayOrder": 2,
    "ShowSummaryChangeOption": "N"
  },
  {
    "LiveFrom": "17/11/2021",
    "CaseTypeID": "PRLAPPS",
    "CaseEventID": "allegationsOfHarmRevised",
    "CaseFieldID": "allegationsOfHarmRevisedLabel",
    "PageShowCondition": "newAllegationsOfHarmYesNo=\"Yes\"",
    "DisplayContext": "READONLY",
    "PageID": 2,
    "PageDisplayOrder": 2,
    "PageFieldDisplayOrder": 2
  },
  {
    "LiveFrom": "17/11/2021",
    "CaseTypeID": "PRLAPPS",
    "CaseEventID": "allegationsOfHarmRevised",
    "CaseFieldID": "newAllegationsOfHarmDomesticAbuseYesNo",
    "DisplayContext": "OPTIONAL",
    "PageID": 2,
    "PageDisplayOrder": 2,
    "PageFieldDisplayOrder": 3,
    "ShowSummaryChangeOption": "Yes"
  },


  {
    "LiveFrom": "03/11/2021",
    "CaseTypeID": "PRLAPPS",
    "CaseEventID": "allegationsOfHarmRevised",
    "CaseFieldID": "submissionRequiredFieldsInfo3",
    "PageFieldDisplayOrder": 1,
    "DisplayContext": "READONLY",
    "PageID": 3,
    "PageDisplayOrder": 3,
    "ShowSummaryChangeOption": "N"
  },
  {
    "LiveFrom": "18/11/2021",
    "CaseTypeID": "PRLAPPS",
    "CaseEventID": "allegationsOfHarmRevised",
    "CaseFieldID": "domesticAbuseBehaviours",
    "DisplayContext": "COMPLEX",
    "PageID": 3,
    "PageDisplayOrder": 3,
    "PageShowCondition": "newAllegationsOfHarmYesNo=\"Yes\"",
    "PageFieldDisplayOrder": 2,
    "ShowSummaryChangeOption": "Yes"
  },
  {
    "LiveFrom": "17/11/2021",
    "CaseTypeID": "PRLAPPS",
    "CaseEventID": "allegationsOfHarmRevised",
    "CaseFieldID": "newAllegationsOfHarmChildAbductionYesNo",
    "DisplayContext": "OPTIONAL",
    "PageID": 2,
    "PageDisplayOrder": 2,
    "PageFieldDisplayOrder": 9,
    "ShowSummaryChangeOption": "Yes"
  },
  {
    "LiveFrom": "17/11/2021",
    "CaseTypeID": "PRLAPPS",
    "CaseEventID": "allegationsOfHarmRevised",
    "CaseFieldID": "newChildAbductionReasons",
    "DisplayContext": "OPTIONAL",
    "FieldShowCondition": "newAllegationsOfHarmChildAbductionYesNo=\"Yes\"",
    "PageID": 2,
    "PageDisplayOrder": 2,
    "PageFieldDisplayOrder": 10,
    "ShowSummaryChangeOption": "Yes"
  },

  {
    "LiveFrom": "03/11/2021",
    "CaseTypeID": "PRLAPPS",
    "CaseEventID": "allegationsOfHarmRevised",
    "CaseFieldID": "submissionRequiredFieldsInfo3",
    "PageFieldDisplayOrder": 1,
    "DisplayContext": "READONLY",
    "PageID": 3,
    "PageDisplayOrder": 3,
    "ShowSummaryChangeOption": "N"
  },

  {
    "LiveFrom": "17/11/2021",
    "CaseTypeID": "PRLAPPS",
    "CaseEventID": "allegationsOfHarmRevised",
    "CaseFieldID": "newPreviousAbductionThreats",
    "DisplayContext": "OPTIONAL",
    "FieldShowCondition": "newAllegationsOfHarmChildAbductionYesNo=\"Yes\"",
    "PageID": 3,
    "PageDisplayOrder": 3,
    "PageFieldDisplayOrder": 1,
    "ShowSummaryChangeOption": "Yes"
  },
  {
    "LiveFrom": "17/11/2021",
    "CaseTypeID": "PRLAPPS",
    "CaseEventID": "allegationsOfHarmRevised",
    "CaseFieldID": "newPreviousAbductionThreatsDetails",
    "DisplayContext": "OPTIONAL",
    "FieldShowCondition": "newAllegationsOfHarmChildAbductionYesNo=\"Yes\" AND newPreviousAbductionThreats=\"Yes\"",
    "PageID": 3,
    "PageDisplayOrder": 3,
    "PageFieldDisplayOrder": 2,
    "ShowSummaryChangeOption": "Yes"
  },
  {
    "LiveFrom": "17/11/2021",
    "CaseTypeID": "PRLAPPS",
    "CaseEventID": "allegationsOfHarmRevised",
    "CaseFieldID": "newChildrenLocationNow",
    "DisplayContext": "OPTIONAL",
    "FieldShowCondition": "newAllegationsOfHarmChildAbductionYesNo=\"Yes\"",
    "PageID": 3,
    "PageDisplayOrder": 3,
    "PageFieldDisplayOrder": 3,
    "ShowSummaryChangeOption": "Yes"
  },
  {
    "LiveFrom": "17/11/2021",
    "CaseTypeID": "PRLAPPS",
    "CaseEventID": "allegationsOfHarmRevised",
    "CaseFieldID": "newAbductionPassportOfficeNotified",
    "DisplayContext": "OPTIONAL",
    "FieldShowCondition": "newAllegationsOfHarmChildAbductionYesNo=\"Yes\"",
    "PageID": 3,
    "PageDisplayOrder": 3,
    "PageFieldDisplayOrder": 3,
    "ShowSummaryChangeOption": "Yes"
  },
  {
    "LiveFrom": "17/11/2021",
    "CaseTypeID": "PRLAPPS",
    "CaseEventID": "allegationsOfHarmRevised",
    "CaseFieldID": "newAbductionChildHasPassport",
    "DisplayContext": "OPTIONAL",
    "FieldShowCondition": "newAllegationsOfHarmChildAbductionYesNo=\"Yes\"",
    "PageID": 3,
    "PageDisplayOrder": 3,
    "PageFieldDisplayOrder": 4,
    "ShowSummaryChangeOption": "Yes"
  },
  {
    "LiveFrom": "17/11/2021",
    "CaseTypeID": "PRLAPPS",
    "CaseEventID": "allegationsOfHarmRevised",
    "CaseFieldID": "newAbductionChildPassportPosession",
    "DisplayContext": "OPTIONAL",
    "FieldShowCondition": "newAllegationsOfHarmChildAbductionYesNo=\"Yes\"",
    "PageID": 3,
    "PageDisplayOrder": 3,
    "PageFieldDisplayOrder": 5,
    "ShowSummaryChangeOption": "Yes"
  },
  {
    "LiveFrom": "17/11/2021",
    "CaseTypeID": "PRLAPPS",
    "CaseEventID": "allegationsOfHarmRevised",
    "CaseFieldID": "newAbductionChildPassportPosessionOtherDetail",
    "DisplayContext": "OPTIONAL",
    "FieldShowCondition": "newAllegationsOfHarmChildAbductionYesNo=\"Yes\" AND newAbductionChildPassportPosession=\"other\"",
    "PageID": 3,
    "PageDisplayOrder": 3,
    "PageFieldDisplayOrder": 6,
    "ShowSummaryChangeOption": "Yes"
  },
  {
    "LiveFrom": "17/11/2021",
    "CaseTypeID": "PRLAPPS",
    "CaseEventID": "allegationsOfHarmRevised",
    "CaseFieldID": "newAbductionPreviousPoliceInvolvement",
    "DisplayContext": "OPTIONAL",
    "FieldShowCondition": "newAllegationsOfHarmChildAbductionYesNo=\"Yes\"",
    "PageID": 3,
    "PageDisplayOrder": 3,
    "PageFieldDisplayOrder": 7,
    "ShowSummaryChangeOption": "Yes"
  },
  {
    "LiveFrom": "17/11/2021",
    "CaseTypeID": "PRLAPPS",
    "CaseEventID": "allegationsOfHarmRevised",
    "CaseFieldID": "newAbductionPreviousPoliceInvolvementDetails",
    "DisplayContext": "OPTIONAL",
    "FieldShowCondition": "newAllegationsOfHarmChildAbductionYesNo=\"Yes\" AND newAbductionPreviousPoliceInvolvement=\"Yes\"",
    "PageID": 3,
    "PageDisplayOrder": 3,
    "PageFieldDisplayOrder": 8,
    "ShowSummaryChangeOption": "Yes"
  },
  {
    "LiveFrom": "17/11/2021",
    "CaseTypeID": "PRLAPPS",
    "CaseEventID": "allegationsOfHarmRevised",
    "CaseFieldID": "newAllegationsOfHarmChildAbuseYesNo",
    "DisplayContext": "OPTIONAL",
    "PageID": 2,
    "PageDisplayOrder": 2,
    "PageFieldDisplayOrder": 9,
    "ShowSummaryChangeOption": "Yes"
  },

  {
    "LiveFrom": "03/11/2021",
    "CaseTypeID": "PRLAPPS",
    "CaseEventID": "allegationsOfHarmRevised",
    "CaseFieldID": "submissionRequiredFieldsInfo4",
    "PageFieldDisplayOrder": 1,
    "DisplayContext": "READONLY",
    "PageID": 4,
    "PageDisplayOrder": 4,
    "ShowSummaryChangeOption": "N"
  },
  {
    "LiveFrom": "18/11/2021",
    "CaseTypeID": "PRLAPPS",
    "CaseEventID": "allegationsOfHarmRevised",
    "CaseFieldID": "domesticAbuseBehaviours",
    "DisplayContext": "COMPLEX",
    "PageID": 4,
    "PageDisplayOrder": 4,
    "PageShowCondition": "newAllegationsOfHarmYesNo=\"Yes\"",
    "PageFieldDisplayOrder": 2,
    "ShowSummaryChangeOption": "Yes"
  },
  {
    "LiveFrom": "03/11/2021",
    "CaseTypeID": "PRLAPPS",
    "CaseEventID": "allegationsOfHarmRevised",
    "CaseFieldID": "submissionRequiredFieldsInfo4",
    "PageFieldDisplayOrder": 1,
    "DisplayContext": "READONLY",
    "PageID": 5,
    "PageDisplayOrder": 5,
    "ShowSummaryChangeOption": "N"
  },
  {
    "LiveFrom": "18/11/2021",
    "CaseTypeID": "PRLAPPS",
    "CaseEventID": "allegationsOfHarmRevised",
    "CaseFieldID": "newAllegationsOfHarmOtherConcernsLabel",
    "DisplayContext": "READONLY",
    "PageID": 5,
    "PageDisplayOrder": 5,
    "PageShowCondition": "newAllegationsOfHarmYesNo=\"Yes\"",
    "PageFieldDisplayOrder": 2
  },
  {
    "LiveFrom": "18/11/2021",
    "CaseTypeID": "PRLAPPS",
    "CaseEventID": "allegationsOfHarmRevised",
    "CaseFieldID": "newAllegationsOfHarmOtherConcerns",
    "DisplayContext": "OPTIONAL",
    "PageID": 5,
    "PageDisplayOrder": 5,
    "PageFieldDisplayOrder": 3,
    "ShowSummaryChangeOption": "Yes"
  },
  {
    "LiveFrom": "18/11/2021",
    "CaseTypeID": "PRLAPPS",
    "CaseEventID": "allegationsOfHarmRevised",
    "CaseFieldID": "newAllegationsOfHarmOtherConcernsDetails",
    "DisplayContext": "OPTIONAL",
    "FieldShowCondition": "newAllegationsOfHarmOtherConcerns=\"Yes\"",
    "PageID": 5,
    "PageDisplayOrder": 5,
    "PageFieldDisplayOrder": 4,
    "ShowSummaryChangeOption": "Yes"
  },
  {
    "LiveFrom": "18/11/2021",
    "CaseTypeID": "PRLAPPS",
    "CaseEventID": "allegationsOfHarmRevised",
    "CaseFieldID": "newAllegationsOfHarmOtherConcernsCourtActions",
    "DisplayContext": "OPTIONAL",
    "PageID": 5,
    "PageDisplayOrder": 5,
    "PageFieldDisplayOrder": 5,
    "ShowSummaryChangeOption": "Yes"
  },
  {
    "LiveFrom": "18/11/2021",
    "CaseTypeID": "PRLAPPS",
    "CaseEventID": "allegationsOfHarmRevised",
    "CaseFieldID": "newAllegationsOfHarmChildContactLabel",
    "DisplayContext": "READONLY",
    "PageID": 5,
    "PageDisplayOrder": 5,
    "PageFieldDisplayOrder": 6
  }

]
