[
  {
    "LiveFrom": "05/11/2021",
    "ID": "AllegationsOfHarmDomesticAbuse",
    "ListElementCode": "physicalAbuseVictim",
    "FieldType": "Text",
    "ElementLabel": "Physical abuse",
    "SecurityClassification": "Public"
  },
  {
    "LiveFrom": "05/11/2021",
    "ID": "AllegationsOfHarmDomesticAbuse",
    "ListElementCode": "emotionalAbuseVictim",
    "FieldType": "Text",
    "ElementLabel": "Emotional abuse",
    "SecurityClassification": "Public"
  },
  {
    "LiveFrom": "05/11/2021",
    "ID": "AllegationsOfHarmDomesticAbuse",
    "ListElementCode": "psychologicalAbuseVictim",
    "FieldType": "Text",
    "ElementLabel": "Psychological abuse",
    "SecurityClassification": "Public"
  },
  {
    "LiveFrom": "05/11/2021",
    "ID": "AllegationsOfHarmDomesticAbuse",
    "ListElementCode": "sexualAbuseVictim",
    "FieldType": "Text",
    "ElementLabel": "Sexual abuse",
    "SecurityClassification": "Public"
  },
  {
    "LiveFrom": "05/11/2021",
    "ID": "AllegationsOfHarmDomesticAbuse",
    "ListElementCode": "financialAbuseVictim",
    "FieldType": "Text",
    "ElementLabel": "Financial abuse",
    "SecurityClassification": "Public"
  },
  {
    "LiveFrom": "20/08/2021",
    "ID": "AllegationsOfHarmDomesticAbuse",
    "ListElementCode": "addNewDomesticAbuseBehaviourLabel",
    "FieldType": "Label",
    "ElementLabel": "## Add new behaviour",
    "SecurityClassification": "Public"
  }
]