[
  {
    "LiveFrom": "20/08/2021",
    "CaseTypeID": "PRLAPPS",
    "ID": "childrenNotPartInTheCaseYesNo",
    "Label": "Do you or respondents have other children who are not part of this application?",
    "FieldType": "YesOrNo",
    "SecurityClassification": "Public"
  },
  {
    "LiveFrom": "20/08/2021",
    "CaseTypeID": "PRLAPPS",
    "ID": "childrenNotInTheCase",
    "Label": "*Child",
    "Min": "1",
    "FieldType": "Collection",
    "FieldTypeParameter": "ChildrenNotInTheCase",
    "SecurityClassification": "Public"
  }
]