[
  {
    "LiveFrom": "05/11/2021",
    "CaseTypeID": "PRLAPPS",
    "CaseEventID": "adminAddLocalAuthority",
    "AccessControl": [
      {
        "UserRoles": [
          "caseworker-privatelaw-courtadmin",
          "caseworker-privatelaw-superuser"
        ],
        "CRUD": "CRUD"
      },
      {
        "UserRoles": [
          "[APPLICANTSOLICITOR]",
          "[CREATOR]",
          "caseworker-privatelaw-judge",
          "caseworker-privatelaw-la"
        ],
        "CRUD": "R"
      }
    ]
  },
  {
    "LiveFrom": "01/01/2025",
    "CaseTypeID": "PRLAPPS",
    "CaseEventID": "adminRemoveLocalAuthority",
    "AccessControl": [
      {
        "UserRoles": [
          "caseworker-privatelaw-courtadmin",
          "caseworker-privatelaw-superuser"
        ],
        "CRUD": "CRUD"
      },
      {
        "UserRoles": [
          "caseworker-privatelaw-la",
          "caseworker-privatelaw-judge"
        ],
        "CRUD": "R"
      }
    ]
  }
]
