[
  {
    "LiveFrom": "01/01/2017",
    "CaseTypeID": "PRLAPPS",
    "ID": "selectedFlags",
    "Label": " ",
    "FieldType": "Collection",
    "FieldTypeParameter": "Flags",
    "SecurityClassification": "Public",
    "Searchable": "N",
    "RetainHiddenValue": "Y"
  },
  {
    "LiveFrom": "01/01/2017",
    "CaseTypeID": "PRLAPPS",
    "ID": "caApplicantBarrister1InternalFlags",
    "Label": " ",
    "FieldType": "Flags",
    "SecurityClassification": "Public",
    "Searchable": "N",
    "RetainHiddenValue": "Y"
  },
  {
    "LiveFrom": "01/01/2017",
    "CaseTypeID": "PRLAPPS",
    "ID": "caApplicantBarrister2InternalFlags",
    "Label": " ",
    "FieldType": "Flags",
    "SecurityClassification": "Public",
    "Searchable": "N",
    "RetainHiddenValue": "Y"
  },
  {
    "LiveFrom": "01/01/2017",
    "CaseTypeID": "PRLAPPS",
    "ID": "caApplicantBarrister3InternalFlags",
    "Label": " ",
    "FieldType": "Flags",
    "SecurityClassification": "Public",
    "Searchable": "N",
    "RetainHiddenValue": "Y"
  },
  {
    "LiveFrom": "01/01/2017",
    "CaseTypeID": "PRLAPPS",
    "ID": "caApplicantBarrister4InternalFlags",
    "Label": " ",
    "FieldType": "Flags",
    "SecurityClassification": "Public",
    "Searchable": "N",
    "RetainHiddenValue": "Y"
  },
  {
    "LiveFrom": "01/01/2017",
    "CaseTypeID": "PRLAPPS",
    "ID": "caApplicantBarrister5InternalFlags",
    "Label": " ",
    "FieldType": "Flags",
    "SecurityClassification": "Public",
    "Searchable": "N",
    "RetainHiddenValue": "Y"
  }
]
