[
  {
    "LiveFrom": "10/08/2021",
    "CaseTypeID": "PRLAPPS",
    "CaseEventID": "c100CreateFlags",
    "CaseFieldID": "flagLauncher",
    "DisplayContext": "MANDATORY",
    "DisplayContextParameter": "#ARGUMENT(CREATE)",
    "PageID": 1,
    "PageDisplayOrder": 1,
    "PageFieldDisplayOrder": 1,
    "ShowSummaryChangeOption": "Yes"
  },
  {
    "LiveFrom": "10/08/2021",
    "CaseTypeID": "PRLAPPS",
    "CaseEventID": "c100CreateFlags",
    "CaseFieldID": "applicants",
    "DisplayContext": "COMPLEX",
    "PageID": 1,
    "PageDisplayOrder": 1,
    "PageFieldDisplayOrder": 2,
    "FieldShowCondition": "flagLauncher=\"DUMMY_VALUE_TO_HIDE_FIELD\"",
    "RetainHiddenValue": "Y",
    "ShowSummaryChangeOption": "Yes"
  },
  {
    "LiveFrom": "10/08/2021",
    "CaseTypeID": "PRLAPPS",
    "CaseEventID": "c100CreateFlags",
    "CaseFieldID": "respondents",
    "DisplayContext": "COMPLEX",
    "PageID": 1,
    "PageDisplayOrder": 1,
    "PageFieldDisplayOrder": 2,
    "FieldShowCondition": "flagLauncher=\"DUMMY_VALUE_TO_HIDE_FIELD\"",
    "RetainHiddenValue": "Y",
    "ShowSummaryChangeOption": "Yes"
  },
  {
    "LiveFrom": "10/08/2021",
    "CaseTypeID": "PRLAPPS",
    "CaseEventID": "c100CreateFlags",
    "CaseFieldID": "caseFlags",
    "DisplayContext": "OPTIONAL",
    "PageID": 1,
    "PageDisplayOrder": 1,
    "PageFieldDisplayOrder": 2,
    "FieldShowCondition": "flagLauncher=\"DUMMY_VALUE_TO_HIDE_FIELD\"",
    "RetainHiddenValue": "Y",
    "ShowSummaryChangeOption": "Yes"
  },
  {
    "LiveFrom": "10/08/2021",
    "CaseTypeID": "PRLAPPS",
    "CaseEventID": "c100ManageFlags",
    "CaseFieldID": "flagLauncher",
    "DisplayContext": "MANDATORY",
    "DisplayContextParameter": "#ARGUMENT(UPDATE)",
    "PageID": 1,
    "PageDisplayOrder": 1,
    "PageFieldDisplayOrder": 1,
    "ShowSummaryChangeOption": "Yes"
  },
  {
    "LiveFrom": "10/08/2021",
    "CaseTypeID": "PRLAPPS",
    "CaseEventID": "c100ManageFlags",
    "CaseFieldID": "caseFlags",
    "DisplayContext": "OPTIONAL",
    "PageID": 1,
    "PageDisplayOrder": 1,
    "PageFieldDisplayOrder": 2,
    "FieldShowCondition": "flagLauncher=\"DUMMY_VALUE_TO_HIDE_FIELD\"",
    "RetainHiddenValue": "Y",
    "ShowSummaryChangeOption": "Yes"
  },
  {
    "LiveFrom": "10/08/2021",
    "CaseTypeID": "PRLAPPS",
    "CaseEventID": "c100ManageFlags",
    "CaseFieldID": "applicants",
    "DisplayContext": "COMPLEX",
    "PageID": 1,
    "PageDisplayOrder": 1,
    "PageFieldDisplayOrder": 2,
    "FieldShowCondition": "flagLauncher=\"DUMMY_VALUE_TO_HIDE_FIELD\"",
    "RetainHiddenValue": "Y",
    "ShowSummaryChangeOption": "Yes"
  },
  {
    "LiveFrom": "10/08/2021",
    "CaseTypeID": "PRLAPPS",
    "CaseEventID": "c100ManageFlags",
    "CaseFieldID": "respondents",
    "DisplayContext": "COMPLEX",
    "PageID": 1,
    "PageDisplayOrder": 1,
    "PageFieldDisplayOrder": 2,
    "FieldShowCondition": "flagLauncher=\"DUMMY_VALUE_TO_HIDE_FIELD\"",
    "RetainHiddenValue": "Y",
    "ShowSummaryChangeOption": "Yes"
  }
]